phenotypic/__init__.py
phenotypic/__main__.py
phenotypic/phenotypic_cli.py
phenotypic/_shared_modules/__init__.py
phenotypic/_shared_modules/_measurement_info.py
phenotypic/abc_/__init__.py
phenotypic/abc_/_base_operation.py
phenotypic/abc_/_grid_corrector.py
phenotypic/abc_/_grid_finder.py
phenotypic/abc_/_grid_measure.py
phenotypic/abc_/_grid_object_detector.py
phenotypic/abc_/_grid_object_refiner.py
phenotypic/abc_/_grid_operation.py
phenotypic/abc_/_image_corrector.py
phenotypic/abc_/_image_enhancer.py
phenotypic/abc_/_image_operation.py
phenotypic/abc_/_lazy_widget_mixin.py
phenotypic/abc_/_measure_features.py
phenotypic/abc_/_object_detector.py
phenotypic/abc_/_object_refiner.py
phenotypic/abc_/_prefab_pipeline.py
phenotypic/abc_/_threshold_detector.py
phenotypic/analysis/__init__.py
phenotypic/analysis/_edge_correction.py
phenotypic/analysis/_log_growth_model.py
phenotypic/analysis/_tukey_outlier.py
phenotypic/analysis/abc_/__init__.py
phenotypic/analysis/abc_/_model_fitter.py
phenotypic/analysis/abc_/_set_analyzer.py
phenotypic/core/__init__.py
phenotypic/core/_grid_image.py
phenotypic/core/_image.py
phenotypic/core/_image_pipeline.py
phenotypic/core/_image_set.py
phenotypic/core/_imread.py
phenotypic/core/_image_parts/__init__.py
phenotypic/core/_image_parts/_image_color_handler.py
phenotypic/core/_image_parts/_image_data_manager.py
phenotypic/core/_image_parts/_image_grid_handler.py
phenotypic/core/_image_parts/_image_handler.py
phenotypic/core/_image_parts/_image_io_handler.py
phenotypic/core/_image_parts/_image_objects_handler.py
phenotypic/core/_image_parts/accessor_abstracts/__init__.py
phenotypic/core/_image_parts/accessor_abstracts/_color_space_accessor.py
phenotypic/core/_image_parts/accessor_abstracts/_image_accessor_base.py
phenotypic/core/_image_parts/accessor_abstracts/_multichannel_accessor.py
phenotypic/core/_image_parts/accessor_abstracts/_single_channel_accessor.py
phenotypic/core/_image_parts/accessors/__init__.py
phenotypic-0.12.0.dist-info/licenses/LICENSE
phenotypic-0.12.0.dist-info/METADATA
phenotypic-0.12.0.dist-info/WHEEL
phenotypic-0.12.0.dist-info/entry_points.txt
phenotypic-0.12.0.dist-info/top_level.txt
phenotypic-0.12.0.dist-info/RECORD
