Metadata-Version: 2.4
Name: phenotypic
Version: 0.12.0
Summary: An image processing framework created for Ex-FAB NSF BioFoundry that aims to streamline the development of image processing pipelines for images analysis of phenotypes.
Author-email: Alexander Nguyen <xander-git@protonmail.com>
Project-URL: Repository, https://github.com/Wheeldon-Lab/PhenoTypic
Classifier: Development Status :: 2 - Pre-Alpha
Classifier: License :: OSI Approved :: GNU General Public License v3 (GPLv3)
Classifier: Natural Language :: English
Classifier: Programming Language :: Python
Classifier: Programming Language :: Python :: 3.10
Classifier: Programming Language :: Python :: 3.11
Classifier: Programming Language :: Python :: 3.12
Requires-Python: <3.13,>=3.10
License-File: LICENSE
Requires-Dist: pandas[compression,computation,excel,hdf5,output-formatting,performance,plot]
Requires-Dist: numpy
Requires-Dist: seaborn
Requires-Dist: scikit-image
Requires-Dist: scikit-learn
Requires-Dist: scipy
Requires-Dist: opencv-python
Requires-Dist: h5py
Requires-Dist: mahotas
Requires-Dist: pillow
Requires-Dist: tqdm
Requires-Dist: mmh3
Requires-Dist: plotly-express>=0.4.1
Requires-Dist: psutil>=7.0.0
Requires-Dist: colour-science>=0.4.6
Requires-Dist: rawpy; sys_platform != "win32"
Requires-Dist: threadpoolctl>=3.6.0
Requires-Dist: pympler>=1.0.1
Requires-Dist: exifread>=3.5.1
Requires-Dist: click>=8.3.0
Requires-Dist: bm3d>=4.0.3
Provides-Extra: jupyter
Requires-Dist: ipywidgets>=8.1.7; extra == "jupyter"
Requires-Dist: jupyter>=1.1.1; extra == "jupyter"
Dynamic: license-file
